matrix_http_rendezvous_synapse-0.1.12.dist-info/METADATA
matrix_http_rendezvous_synapse-0.1.12.dist-info/WHEEL
matrix_http_rendezvous_synapse/__init__.py
matrix_http_rendezvous_synapse/matrix_http_rendezvous_synapse.abi3.so
matrix_http_rendezvous_synapse-0.1.12.dist-info/RECORD
